Workbook

Sheet Summary
A1: UC-F10 / UC-F11 major-component BOM cost
A3: Build quantity | B3: 1000 | D3: Cost metric | E3: Per unit | F3: 1,000 units | G3: Confidence | H3: Meaning
A4: Currency | B4: USD | D4: UC-F10 sourced subtotal | E4: =SUMIF('BOM detail'!$B$4:$B$14,"UC-F10",'BOM detail'!$J$4:$J$14) -> 5.99496 | F4: =E4*$B$3 -> 5994.96 | G4: Medium | H4: Public pricing; some stock and packaging constraints remain
A5: Pricing date | B5: 46226 | D5: UC-F11 sourced subtotal, excl. IMX501 | E5: =SUMIFS('BOM detail'!$J$4:$J$14,'BOM detail'!$B$4:$B$14,"UC-F11",'BOM detail'!$H$4:$H$14,"<>Budget estimate") -> 13.37326 | F5: =E5*$B$3 -> 13373.26 | G5: Low | H5: Includes discontinued LN023 retail reference; excludes IMX501
A6: Scope | B6: Major components visible in screenshot only | D6: Combined sourced subtotal, excl. IMX501 | E6: =E4+E5 -> 19.36822 | F6: =E6*$B$3 -> 19368.22 | G6: Medium | H6: Purchasable-price view before the image sensor
A7: Freight / VAT / duty | B7: Excluded | D7: IMX501 budget allowance | E7: =SUMIFS('BOM detail'!$J$4:$J$14,'BOM detail'!$H$4:$H$14,"Budget estimate") -> 135 | F7: =E7*$B$3 -> 135000 | G7: Low | H7: Uses an editable planning allowance, not a supplier quotation
A8: Camera sensor basis | B8: Budgetary allowance; supplier RFQ required | D8: Combined budgetary total | E8: =E6+E7 -> 154.36822 | F8: =E8*$B$3 -> 154368.22 | G8: Low | H8: Planning figure only; replace the IMX501 allowance after RFQ
A11: Key procurement findings
A12: • IMX501-AACK-C has no public 1,000-piece price. Obtain a formal quote from Sony/FRAMOS/Macnica before freezing COGS.
A13: • LN023 is discontinued and publicly listed as out of stock. Confirm whether the BOM means the complete lens + M12 adapter set.
A14: • RS0104YQ demand is 2,000 pcs. The checked LCSC stock was 1,959 pcs, leaving a 41-piece shortfall before attrition.
A15: • AP3428WT-7 public 1k pricing exists, but the checked DigiKey stock was only 112 pcs; Mouser showed 3,738 pcs at a 3,000-piece full-reel tier.
A16: • Prices exclude smaller passives, PCB, assembly, test, yield loss, logistics, VAT, duty, and supplier negotiation.

Sheet BOM detail
A1: Detailed cost model, 1,000 finished units
A3: Line | B3: Board | C3: MPN from screenshot | D3: Normalized MPN / description | E3: Qty / unit | F3: Required qty | G3: Supplier / basis | H3: Price type | I3: Unit price (USD) | J3: Extended / finished unit | K3: Extended / 1,000 units | L3: Stock checked | M3: Gap vs required | N3: Risk / action | O3: Source ID
A4: 1 | B4: UC-F10 | C4: W25Q128JVPIQ | D4: Winbond 128-Mbit SPI/QPI NOR, 8-WSON | E4: 1 | F4: =E4*Summary!$B$3 -> 1000 | G4: LCSC, 700+ tier | H4: Public price | I4: 2.6237 | J4: =E4*I4 -> 2.6237 | K4: =F4*I4 -> 2623.7 | L4: 13664 | M4: =IF(L4="","",L4-F4) -> 12664 | N4: Enough public stock; 1,000-unit order qualifies for 700+ tier | O4: S1
A5: 2 | B5: UC-F10 | C5: ESP-PSRAM64H | D5: Espressif 64-Mbit 3.3 V PSRAM, SOIC-8 | E5: 1 | F5: =E5*Summary!$B$3 -> 1000 | G5: DigiKey / Adafruit retail | H5: Public price | I5: 1.75 | J5: =E5*I5 -> 1.75 | K5: =F5*I5 -> 1750 | L5: 6087 | M5: =IF(L5="","",L5-F5) -> 5087 | N5: No published volume tier; request direct Espressif/EMS quote | O5: S2
A6: 3 | B6: UC-F10 | C6: RP2350A | D6: Raspberry Pi MCU, QFN-60 | E6: 1 | F6: =E6*Summary!$B$3 -> 1000 | G6: Raspberry Pi 7-inch reel, 500 pcs | H6: Manufacturer list | I6: 0.9 | J6: =E6*I6 -> 0.9 | K6: =F6*I6 -> 900 | M6: =IF(L6="","",L6-F6) | N6: Two 500-piece reels meet 1,000-unit build; confirm reseller price | O6: S3
A7: 4 | B7: UC-F10 | C7: AP7331-18WG | D7: AP7331-18WG-7, 1.8 V / 300 mA LDO | E7: 1 | F7: =E7*Summary!$B$3 -> 1000 | G7: DigiKey, 1,000+ tier | H7: Public price | I7: 0.12485 | J7: =E7*I7 -> 0.12485 | K7: =F7*I7 -> 124.85 | L7: 30409 | M7: =IF(L7="","",L7-F7) -> 29409 | N7: Screenshot omits -7 packing suffix; normalized to reel/cut-tape orderable MPN | O7: S4
A8: 5 | B8: UC-F10 | C8: AP3428WT-7 | D8: Diodes Inc. 1 A adjustable buck, TSOT-25 | E8: 1 | F8: =E8*Summary!$B$3 -> 1000 | G8: DigiKey, 1,000+ tier | H8: Public price | I8: 0.10141 | J8: =E8*I8 -> 0.10141 | K8: =F8*I8 -> 101.41 | L8: 112 | M8: =IF(L8="","",L8-F8) -> -888 | N8: Public stock below requirement; seek 3k reel or alternate distributor | O8: S5
A9: 6 | B9: UC-F10 | C9: RS0104YQ | D9: Runic 4-bit bidirectional level translator, TSSOP-14 | E9: 2 | F9: =E9*Summary!$B$3 -> 2000 | G9: LCSC, 100+ tier | H9: Public price | I9: 0.2475 | J9: =E9*I9 -> 0.495 | K9: =F9*I9 -> 495 | L9: 1959 | M9: =IF(L9="","",L9-F9) -> -41 | N9: Needs 2,000 pcs; public stock is 41 pcs short before attrition | O9: S6
A10: 7 | B10: UC-F11 | C10: AP7331-28WG | D10: AP7331-28WG-7, 2.8 V / 300 mA LDO | E10: 1 | F10: =E10*Summary!$B$3 -> 1000 | G10: Mouser, 500+ tier | H10: Public price | I10: 0.157 | J10: =E10*I10 -> 0.157 | K10: =F10*I10 -> 157 | L10: 782 | M10: =IF(L10="","",L10-F10) -> -218 | N10: 218 pcs short in immediate stock; 12k shown on order | O10: S7
A11: 8 | B11: UC-F11 | C11: AP7331-18WG | D11: AP7331-18WG-7, 1.8 V / 300 mA LDO | E11: 1 | F11: =E11*Summary!$B$3 -> 1000 | G11: DigiKey, 1,000+ tier | H11: Public price | I11: 0.12485 | J11: =E11*I11 -> 0.12485 | K11: =F11*I11 -> 124.85 | L11: 30409 | M11: =IF(L11="","",L11-F11) -> 29409 | N11: Screenshot omits -7 packing suffix | O11: S4
A12: 9 | B12: UC-F11 | C12: AP3428WT-7 | D12: Diodes Inc. 1 A adjustable buck, TSOT-25 | E12: 1 | F12: =E12*Summary!$B$3 -> 1000 | G12: DigiKey, 1,000+ tier | H12: Public price | I12: 0.10141 | J12: =E12*I12 -> 0.10141 | K12: =F12*I12 -> 101.41 | L12: 112 | M12: =IF(L12="","",L12-F12) -> -888 | N12: Public stock below requirement | O12: S5
A13: 10 | B13: UC-F11 | C13: IMX501-AACK-C | D13: Sony 12.3 MP packaged intelligent vision sensor | E13: 1 | F13: =E13*Summary!$B$3 -> 1000 | G13: Planning allowance; replace after RFQ | H13: Budget estimate | I13: 135 | J13: =E13*I13 -> 135 | K13: =F13*I13 -> 135000 | M13: =IF(L13="","",L13-F13) | N13: No public 1k quote. $135 is an editable budget placeholder based on Sony's historical ¥20,000 sample price, discounted for volume | O13: S8
A14: 11 | B14: UC-F11 | C14: LN023 | D14: Arducam M23430M14, 1/2.3-inch 6 mm M12 lens + adapter | E14: 1 | F14: =E14*Summary!$B$3 -> 1000 | G14: Arducam / Welectron retail reference | H14: Discontinued reference | I14: 12.99 | J14: =E14*I14 -> 12.99 | K14: =F14*I14 -> 12990 | L14: 0 | M14: =IF(L14="","",L14-F14) -> -1000 | N14: Discontinued / out of stock; identify production replacement and volume quote | O14: S9
A16: Totals by board
A17: Metric | B17: Per unit | C17: For 1,000 units
A18: UC-F10 | B18: =SUMIF($B$4:$B$14,"UC-F10",$J$4:$J$14) -> 5.99496 | C18: =B18*Summary!$B$3 -> 5994.96
A19: UC-F11 including sensor allowance | B19: =SUMIF($B$4:$B$14,"UC-F11",$J$4:$J$14) -> 148.37326 | C19: =B19*Summary!$B$3 -> 148373.26
A20: Combined | B20: =SUM($B$18:$B$19) -> 154.36822 | C20: =B20*Summary!$B$3 -> 154368.22

Sheet Sources
A1: Pricing and identification sources
A3: ID | B3: MPN | C3: Supplier / publisher | D3: Price or fact used | E3: Checked | F3: URL | G3: Notes
A4: S1 | B4: W25Q128JVPIQ | C4: LCSC | D4: $2.6237 at 700+; 13,664 stock | E4: 46226 | F4: https://www.lcsc.com/product-detail/C190862.html | G4: 1,000 pcs qualifies for the 700+ tier
A5: S2 | B5: ESP-PSRAM64H | C5: DigiKey / Adafruit | D5: $1.75 each; 6,087 stock | E5: 46226 | F5: https://www.digikey.com/en/products/detail/adafruit-industries-llc/4677/13148775 | G5: Retail breakout price; volume RFQ recommended
A6: S3 | B6: RP2350A | C6: Raspberry Pi | D6: $0.90 each on 500-piece 7-inch reel | E6: 46226 | F6: https://www.raspberrypi.com/news/rp2350-now-available-to-buy-a-high-performance-secure-microcontroller-for-your-next-project/ | G6: Two reels assumed for 1,000 units
A7: S4 | B7: AP7331-18WG-7 | C7: DigiKey | D7: $0.12485 at 1,000+; 30,409 stock | E7: 46226 | F7: https://www.digikey.com/en/products/detail/diodes-incorporated/AP7331-18WG-7/2182601 | G7: Public distributor price
A8: S5 | B8: AP3428WT-7 | C8: DigiKey | D8: $0.10141 at 1,000+; 112 stock | E8: 46226 | F8: https://www.digikey.com/en/products/detail/diodes-incorporated/AP3428WT-7/13930252 | G8: Price tier available, immediate stock insufficient
A9: S6 | B9: RS0104YQ | C9: LCSC | D9: $0.2475 at 100+; 1,959 stock | E9: 46226 | F9: https://www.lcsc.com/product-detail/C2762288.html | G9: Public page requests RFQ above 100 pcs; price carried as budget basis
A10: S7 | B10: AP7331-28WG-7 | C10: Mouser | D10: $0.157 at 500+; 782 stock; 12,000 on order | E10: 46226 | F10: https://www.mouser.com/en/ProductDetail/Diodes-Incorporated/AP7331-28WG-7 | G10: 1,000 units uses the 500+ tier
A11: S8 | B11: IMX501-AACK-C | C11: Sony | D11: Historical sample price ¥20,000; public 1k price unavailable | E11: 46226 | F11: https://www.sony.com/en/SonyInfo/News/Press/202005/20-037E/ | G11: Workbook uses $135 planning allowance. Replace after authorized distributor RFQ
A12: S9 | B12: LN023 / M23430M14 | C12: Arducam / Welectron | D12: Retail reference $12.99 / €12.02 ex VAT; discontinued/out of stock | E12: 46226 | F12: https://www.welectron.com/Arducam-LN023-M23430M14-M12-S-Mount-Lens-with-Adapter-for-HQ-Camera-1-23-6mm | G12: Confirm whether lens holder/adapter is included in production BOM
